glearn-0.23.3.dist-info/WHEEL
glearn-0.23.3.dist-info/top_level.txt
glearn-0.23.3.dist-info/RECORD
glearn-0.23.3.dist-info/AUTHORS.txt
glearn-0.23.3.dist-info/LICENSE.txt
glearn-0.23.3.dist-info/METADATA
glearn.libs/libgomp-a34b3233.so.1.0.0
scripts/fix_libomp.sh
glearn/__version__.py
glearn/__init__.py
glearn/_load_omp/load_omp.pyx
glearn/_load_omp/__init__.py
glearn/_load_omp/load_omp.cpython-310-x86_64-linux-gnu.so
glearn/priors/normal.py
glearn/priors/cauchy.py
glearn/priors/prior.py
glearn/priors/inverse_gamma.py
glearn/priors/student_t.py
glearn/priors/gamma.py
glearn/priors/beta_prime.py
glearn/priors/erlang.py
glearn/priors/uniform.py
glearn/priors/__init__.py
glearn/_mean/linear_model.py
glearn/_mean/__init__.py
glearn/_optimize/root.py
glearn/_optimize/_minimize_terminator.py
glearn/_optimize/minimize.py
glearn/_optimize/__init__.py
glearn/_optimize/_chandrupatla.py
glearn/_gaussian_process/_posterior.py
glearn/_gaussian_process/_gaussian_process_utilities.py
glearn/_gaussian_process/gaussian_process.py
glearn/_gaussian_process/__init__.py
glearn/device/_timer.py
glearn/device/_cuda.py
glearn/device/_info.py
glearn/device/_device.py
glearn/device/_memory.py
glearn/device/__init__.py
glearn/kernels/rational_quadratic.cpython-310-x86_64-linux-gnu.so
glearn/kernels/rational_quadratic.pyx
glearn/kernels/kernel.pyx
glearn/kernels/exponential.pxd
glearn/kernels/square_exponential.pyx
glearn/kernels/matern.pxd
glearn/kernels/linear.cpython-310-x86_64-linux-gnu.so
glearn/kernels/square_exponential.cpython-310-x86_64-linux-gnu.so
glearn/kernels/__init__.pxd
glearn/kernels/matern.pyx
glearn/kernels/exponential.cpython-310-x86_64-linux-gnu.so
glearn/kernels/rational_quadratic.pxd
glearn/kernels/square_exponential.pxd
glearn/kernels/linear.pxd
glearn/kernels/linear.pyx
glearn/kernels/kernel.cpython-310-x86_64-linux-gnu.so
glearn/kernels/kernel.pxd
glearn/kernels/matern.cpython-310-x86_64-linux-gnu.so
glearn/kernels/__init__.py
glearn/kernels/exponential.pyx
glearn/_correlation/_compute_sparse_correlation.cpython-310-x86_64-linux-gnu.so
glearn/_correlation/_euclidean_distance.cpython-310-x86_64-linux-gnu.so
